{
  "currentAgent": "idle",
  "cycleNumber": 176,
  "cycleStartTime": 1776061968963,
  "nextCycleTime": 1776063814908,
  "lastCycleComplete": 1776062014908,
  "activeSquads": [
    "Xyndicate Alpha",
    "Squad Nova"
  ],
  "squadResults": {
    "XYNDICATE_ALPHA": {
      "squadId": "XYNDICATE_ALPHA",
      "squadName": "Xyndicate Alpha",
      "riskMode": "aggressive",
      "baseAsset": "ETH",
      "txHash": "0x19b3d8f646dbb013fa9c5c7ddcf30c105ff7a581e01b18c0d4417342499e9352",
      "vaultTxHash": "0xbcf149e6798b1b578557200fdeeaeaeaeaa97d93c912b32e99201b250e797700",
      "pnlDelta": "50",
      "action": "BUY",
      "asset": "ETH",
      "sizePercent": 100,
      "rationale": "High spread between OKX and Uniswap prices suggests arbitrage opportunity. Analyst confidence is high at 0.8.",
      "route": "uniswap",
      "routingReason": "Uniswap offers a better buy price beyond the 10 bps threshold.",
      "spreadBps": 10000,
      "narratorSummary": "Xyndicate Alpha deployed ETH (100% treasury) via uniswap. High spread between OKX and Uniswap prices suggests arbitrage opportunity. Analyst confidence is high at 0.8.",
      "analyst": {
        "opportunities": [
          {
            "asset": "ETH",
            "type": "short",
            "rationale": "High spread between OKX and Uniswap prices, indicating potential arbitrage opportunity",
            "confidence": 0.8
          }
        ],
        "risks": [
          {
            "description": "High volatility with a 24h change of -0.97%, increasing the risk of losses in short-term trading",
            "severity": 0.9
          }
        ],
        "recommendation": "wait",
        "topAsset": "ETH",
        "confidenceScore": 0.8
      },
      "market": {
        "pair": "ETH-USDT",
        "price": 2196.72,
        "okxPrice": 2196.72,
        "uniswapPrice": 2.196036662537181e-9,
        "spreadBps": 10000,
        "betterRoute": "okx",
        "uniswapPoolId": "0x88e6a0c2ddd26feeb64f039a2c41296fcb3f5640",
        "priceSpreads": {
          "absolute": -2196.7199999978,
          "bps": 10000,
          "source": "uniswap-v3-onchain",
          "rawUniswapPrice": 2.196036662537181e-9,
          "rawOkxPrice": 2196.72,
          "uniswapError": null
        },
        "change24h": -0.9661204156617132
      },
      "narrative": "BUY ETH (100% treasury) via uniswap · High spread between OKX and Uniswap prices suggests arbitrage opportunity. Analyst confidence is high at 0.8."
    },
    "SQUAD_NOVA": {
      "squadId": "SQUAD_NOVA",
      "squadName": "Squad Nova",
      "riskMode": "balanced",
      "baseAsset": "OKB",
      "txHash": "0xf27ae4adf09a5887de13ac6f6a860291f22c571bd7465cd8d2664f0e42eac0fe",
      "vaultTxHash": "0x9fa27363652e7bc211e95faf155fc9ca4caf0d31a55ba142cb1088423988bd9b",
      "pnlDelta": "0",
      "action": "HOLD",
      "asset": "OKB",
      "sizePercent": 100,
      "rationale": "Market pair OKB-USDT has experienced a 24-hour decrease of -0.68%, indicating potential downward pressure. Analyst recommendation is to wait with 60% confidence.",
      "route": "okx",
      "routingReason": "No execution improvement is needed for HOLD, so OKX remains the default route.",
      "spreadBps": 0,
      "narratorSummary": "Squad Nova held OKB (100% treasury) via okx. Market pair OKB-USDT has experienced a 24-hour decrease of -0.68%, indicating potential downward pressure. Analyst recommendation is to wait with 60% confidence.",
      "analyst": {
        "opportunities": [],
        "risks": [
          {
            "description": "The market pair OKB-USDT has experienced a 24-hour decrease of -0.68%, indicating potential downward pressure on the asset.",
            "severity": 2
          }
        ],
        "recommendation": "wait",
        "topAsset": "OKB",
        "confidenceScore": 0.6
      },
      "market": {
        "pair": "OKB-USDT",
        "price": 83.09,
        "okxPrice": 83.09,
        "uniswapPrice": 83.09,
        "spreadBps": 0,
        "betterRoute": "okx",
        "uniswapPoolId": null,
        "priceSpreads": {
          "absolute": 0,
          "bps": 0,
          "source": "okx-fallback",
          "rawUniswapPrice": null,
          "rawOkxPrice": 83.09,
          "uniswapError": null
        },
        "change24h": -0.6813291895768506
      },
      "narrative": "HOLD OKB (100% treasury) via okx · Market pair OKB-USDT has experienced a 24-hour decrease of -0.68%, indicating potential downward pressure. Analyst recommendation is to wait with 60% confidence."
    }
  },
  "slowSquadLastRunAt": {
    "phantom_last_run": 1776062002728,
    "cipher_last_run": 1776062002728,
    "nexus_last_run": 1776062002729
  },
  "agentLog": [
    {
      "agent": "system",
      "status": "started",
      "completedAt": 1776061968963,
      "summary": "Cycle 176 started. Oracle snapshot in progress."
    },
    {
      "agent": "oracle",
      "status": "complete",
      "completedAt": 1776061997785,
      "summary": "ETH $0.00 (0.00%) | Uniswap spread 0.00bps"
    },
    {
      "agent": "analyst",
      "status": "complete",
      "completedAt": 1776061998893,
      "summary": "wait on ETH | confidence 0"
    },
    {
      "agent": "strategist",
      "status": "complete",
      "completedAt": 1776061999642,
      "summary": "HOLD ETH (0% treasury)"
    },
    {
      "agent": "router",
      "status": "complete",
      "completedAt": 1776062000426,
      "summary": "okx selected | spread 0.00bps"
    },
    {
      "agent": "executor",
      "status": "complete",
      "completedAt": 1776062001093,
      "summary": "HOLD executed | tx 0x19b3d8f646dbb013fa9c5c7ddcf30c105ff7a581e01b18c0d4417342499e9352"
    },
    {
      "agent": "narrator",
      "status": "complete",
      "completedAt": 1776062002060,
      "summary": "Xyndicate Alpha deployed ETH (100% treasury) via uniswap. High spread between OKX and Uniswap prices suggests arbitrage opportunity. Analyst confidence is high at 0.8. | Squad Nova held OKB (100% treasury) via okx. Market pair OKB-USDT has experienced a 24-hour decrease of -0.68%, indicating potential downward pressure. Analyst recommendation is to wait with 60% confidence."
    },
    {
      "agent": "slow-phantom",
      "status": "complete",
      "completedAt": 1776062002728,
      "summary": "Phantom Protocol decision logged"
    },
    {
      "agent": "slow-cipher",
      "status": "complete",
      "completedAt": 1776062002728,
      "summary": "Cipher Strategy decision logged"
    },
    {
      "agent": "slow-nexus",
      "status": "complete",
      "completedAt": 1776062002729,
      "summary": "Nexus Quant decision logged"
    },
    {
      "agent": "system",
      "status": "complete",
      "completedAt": 1776062014908,
      "summary": "Cycle 176 complete. Awaiting next scheduled run."
    }
  ]
}
