{
  "currentAgent": "idle",
  "cycleNumber": 296,
  "cycleStartTime": 1776274227459,
  "nextCycleTime": 1776276088541,
  "lastCycleComplete": 1776274288541,
  "activeSquads": [
    "Xyndicate Alpha",
    "Squad Nova"
  ],
  "squadResults": {
    "XYNDICATE_ALPHA": {
      "squadId": "XYNDICATE_ALPHA",
      "squadName": "Xyndicate Alpha",
      "riskMode": "aggressive",
      "baseAsset": "ETH",
      "txHash": "0xf625671c4dba8e097d8963f8a96dccb50eb70a40ca194552a2b1da4e21e771c5",
      "vaultTxHash": "0x456819f425e34c3e862d10599f3da26a1f3f1501cbbad402bb2bdc4b83c54c3e",
      "pnlDelta": "50",
      "action": "BUY",
      "asset": "ETH",
      "sizePercent": 100,
      "rationale": "Positive 24h price change and potential arbitrage opportunity with Uniswap price. High spread between Uniswap and OKX prices indicates potential for profit.",
      "route": "okx",
      "routingReason": "OKX remains within threshold, so default execution path is retained.",
      "spreadBps": 1805133610.9504,
      "narratorSummary": "Xyndicate Alpha deployed ETH (100% treasury) via okx. Positive 24h price change and potential arbitrage opportunity with Uniswap price. High spread between Uniswap and OKX prices indicates potential for profit.",
      "analyst": {
        "opportunities": [
          {
            "asset": "ETH",
            "type": "long",
            "rationale": "Positive 24h price change and potential arbitrage opportunity with Uniswap price",
            "confidence": 0.8
          }
        ],
        "risks": [
          {
            "description": "High spread between Uniswap and OKX prices",
            "severity": 0.9
          }
        ],
        "recommendation": "wait",
        "topAsset": "ETH",
        "confidenceScore": 0.8
      },
      "market": {
        "pair": "ETH-USDT",
        "price": 2353.2,
        "okxPrice": 2353.2,
        "uniswapPrice": 424786394.5288408,
        "spreadBps": 1805133610.95,
        "betterRoute": "uniswap",
        "uniswapPoolId": "0x88e6a0c2ddd26feeb64f039a2c41296fcb3f5640",
        "priceSpreads": {
          "absolute": 424784041.3288408,
          "bps": 1805133610.95,
          "source": "uniswap-v3-onchain",
          "rawUniswapPrice": 424786394.5288408,
          "rawOkxPrice": 2353.2,
          "uniswapError": null
        },
        "change24h": 0.8978415785546893
      },
      "narrative": "BUY ETH (100% treasury) via okx · Positive 24h price change and potential arbitrage opportunity with Uniswap price. High spread between Uniswap and OKX prices indicates potential for profit."
    },
    "SQUAD_NOVA": {
      "squadId": "SQUAD_NOVA",
      "squadName": "Squad Nova",
      "riskMode": "balanced",
      "baseAsset": "OKB",
      "txHash": "0x976800d89bec4f3bf83fef0bf9a62f22c400d535772fa17814578b63741a24fd",
      "vaultTxHash": "0x786e01bd73c5451d9b28b698fee224e9a331ee9a3c0abc6fc6430e0cd2581c11",
      "pnlDelta": "0",
      "action": "HOLD",
      "asset": "OKB",
      "sizePercent": 100,
      "rationale": "Market stability with minimal spread and consistent prices across exchanges. Analyst confidence high at 0.8.",
      "route": "okx",
      "routingReason": "No execution improvement is needed for HOLD, so OKX remains the default route.",
      "spreadBps": 0,
      "narratorSummary": "Squad Nova held OKB (100% treasury) via okx. Market stability with minimal spread and consistent prices across exchanges. Analyst confidence high at 0.8.",
      "analyst": {
        "opportunities": [
          {
            "asset": "OKB",
            "type": "hold",
            "rationale": "The market is currently stable with a minimal spread and no significant price difference between exchanges.",
            "confidence": 0.8
          }
        ],
        "risks": [
          {
            "description": "Negative 24-hour price change may indicate potential volatility.",
            "severity": 0.7
          }
        ],
        "recommendation": "wait",
        "topAsset": "OKB",
        "confidenceScore": 0.8
      },
      "market": {
        "pair": "OKB-USDT",
        "price": 85.64,
        "okxPrice": 85.64,
        "uniswapPrice": 85.64,
        "spreadBps": 0,
        "betterRoute": "okx",
        "uniswapPoolId": null,
        "priceSpreads": {
          "absolute": 0,
          "bps": 0,
          "source": "okx-fallback",
          "rawUniswapPrice": null,
          "rawOkxPrice": 85.64,
          "uniswapError": null
        },
        "change24h": -0.1515681473708703
      },
      "narrative": "HOLD OKB (100% treasury) via okx · Market stability with minimal spread and consistent prices across exchanges. Analyst confidence high at 0.8."
    }
  },
  "slowSquadLastRunAt": {
    "phantom_last_run": 1776274267903,
    "cipher_last_run": 1776274267903,
    "nexus_last_run": 1776274267904
  },
  "uniswapQueriesSuccessful": 0,
  "agentLog": [
    {
      "agent": "system",
      "status": "started",
      "completedAt": 1776274227459,
      "summary": "Cycle 296 started. Oracle snapshot in progress."
    },
    {
      "agent": "oracle",
      "status": "complete",
      "completedAt": 1776274262667,
      "summary": "ETH $0.00 (0.00%) | Uniswap spread 0.00bps"
    },
    {
      "agent": "analyst",
      "status": "complete",
      "completedAt": 1776274263596,
      "summary": "wait on ETH | confidence 0"
    },
    {
      "agent": "strategist",
      "status": "complete",
      "completedAt": 1776274264450,
      "summary": "HOLD ETH (0% treasury)"
    },
    {
      "agent": "router",
      "status": "complete",
      "completedAt": 1776274265389,
      "summary": "okx selected | spread 0.00bps"
    },
    {
      "agent": "executor",
      "status": "complete",
      "completedAt": 1776274266173,
      "summary": "HOLD executed | tx 0xf625671c4dba8e097d8963f8a96dccb50eb70a40ca194552a2b1da4e21e771c5"
    },
    {
      "agent": "narrator",
      "status": "complete",
      "completedAt": 1776274266998,
      "summary": "Xyndicate Alpha deployed ETH (100% treasury) via okx. Positive 24h price change and potential arbitrage opportunity with Uniswap price. High spread between Uniswap and OKX prices indicates potential for profit. | Squad Nova held OKB (100% treasury) via okx. Market stability with minimal spread and consistent prices across exchanges. Analyst confidence high at 0.8."
    },
    {
      "agent": "slow-phantom",
      "status": "complete",
      "completedAt": 1776274267903,
      "summary": "Phantom Protocol decision logged"
    },
    {
      "agent": "slow-cipher",
      "status": "complete",
      "completedAt": 1776274267903,
      "summary": "Cipher Strategy decision logged"
    },
    {
      "agent": "slow-nexus",
      "status": "complete",
      "completedAt": 1776274267904,
      "summary": "Nexus Quant decision logged"
    },
    {
      "agent": "system",
      "status": "complete",
      "completedAt": 1776274288541,
      "summary": "Cycle 296 complete. Awaiting next scheduled run."
    }
  ]
}
