{
  "currentAgent": "oracle",
  "cycleNumber": 523,
  "cycleStartTime": 1777058773902,
  "nextCycleTime": 1777060573902,
  "lastCycleComplete": 1777056948278,
  "activeSquads": [
    "Xyndicate Alpha",
    "Squad Nova"
  ],
  "squadResults": {},
  "slowSquadLastRunAt": {},
  "uniswapQueriesSuccessful": 0,
  "uniswapQueriesTotal": 2,
  "agentLog": [
    {
      "agent": "system",
      "status": "started",
      "completedAt": 1777058773902,
      "summary": "Cycle 523 started. Oracle snapshot in progress."
    }
  ]
}
