{
  "currentAgent": "idle",
  "cycleNumber": 192,
  "cycleStartTime": 1776094283797,
  "nextCycleTime": 1776096125536,
  "lastCycleComplete": 1776094325536,
  "activeSquads": [
    "Xyndicate Alpha",
    "Squad Nova"
  ],
  "squadResults": {
    "XYNDICATE_ALPHA": {
      "squadId": "XYNDICATE_ALPHA",
      "squadName": "Xyndicate Alpha",
      "riskMode": "aggressive",
      "baseAsset": "ETH",
      "txHash": "0x4c96fdf2bf4a3c46df49e0b60d73083d2785eda4894b642067dd6fd3abe332bb",
      "vaultTxHash": "0xb258a7187e57f676caf29f1633596c737e579cefa770f1753e77edeed3755500",
      "pnlDelta": "50",
      "action": "BUY",
      "asset": "ETH",
      "sizePercent": 100,
      "rationale": "Positive 24h price change and potential arbitrage opportunity through Uniswap with high confidence level.",
      "route": "okx",
      "routingReason": "OKX remains within threshold, so default execution path is retained.",
      "spreadBps": 2051397303.1102,
      "narratorSummary": "Xyndicate Alpha deployed ETH (100% treasury) via okx. Positive 24h price change and potential arbitrage opportunity through Uniswap with high confidence level.",
      "analyst": {
        "opportunities": [
          {
            "asset": "ETH",
            "type": "long",
            "rationale": "Positive 24h price change and potential arbitrage opportunity through Uniswap",
            "confidence": 0.8
          }
        ],
        "risks": [
          {
            "description": "High spread between Uniswap and OKX prices",
            "severity": 0.9
          }
        ],
        "recommendation": "wait",
        "topAsset": "ETH",
        "confidenceScore": 0.8
      },
      "market": {
        "pair": "ETH-USDT",
        "price": 2207.51,
        "okxPrice": 2207.51,
        "uniswapPrice": 452850213.56887794,
        "spreadBps": 2051397303.11,
        "betterRoute": "uniswap",
        "uniswapPoolId": "0x88e6a0c2ddd26feeb64f039a2c41296fcb3f5640",
        "priceSpreads": {
          "absolute": 452848006.05887794,
          "bps": 2051397303.11,
          "source": "uniswap-v3-onchain",
          "rawUniswapPrice": 452850213.56887794,
          "rawOkxPrice": 2207.51,
          "uniswapError": null
        },
        "change24h": 1.2619266055045972
      },
      "narrative": "BUY ETH (100% treasury) via okx · Positive 24h price change and potential arbitrage opportunity through Uniswap with high confidence level."
    },
    "SQUAD_NOVA": {
      "squadId": "SQUAD_NOVA",
      "squadName": "Squad Nova",
      "riskMode": "balanced",
      "baseAsset": "OKB",
      "txHash": "0x5c12688d8aad441eee29f0c52e7fba4e78ece08a82a182dacac0f59f154b50ce",
      "vaultTxHash": "0xab1c6ae0aa162bd193365a52d55766340695ca8edc024af780c9d39d7870549a",
      "pnlDelta": "0",
      "action": "HOLD",
      "asset": "OKB",
      "sizePercent": 100,
      "rationale": "Price stable with balanced risk mode. Analyst recommends waiting. Confidence score is 0.8.",
      "route": "okx",
      "routingReason": "No execution improvement is needed for HOLD, so OKX remains the default route.",
      "spreadBps": 0,
      "narratorSummary": "Squad Nova held OKB (100% treasury) via okx. Price stable with balanced risk mode. Analyst recommends waiting. Confidence score is 0.8.",
      "analyst": {
        "opportunities": [
          {
            "asset": "OKB",
            "type": "hold",
            "rationale": "Price stable with balanced risk mode",
            "confidence": 0.8
          }
        ],
        "risks": [],
        "recommendation": "wait",
        "topAsset": "OKB",
        "confidenceScore": 0.8
      },
      "market": {
        "pair": "OKB-USDT",
        "price": 83.01,
        "okxPrice": 83.01,
        "uniswapPrice": 83.01,
        "spreadBps": 0,
        "betterRoute": "okx",
        "uniswapPoolId": null,
        "priceSpreads": {
          "absolute": 0,
          "bps": 0,
          "source": "okx-fallback",
          "rawUniswapPrice": null,
          "rawOkxPrice": 83.01,
          "uniswapError": null
        },
        "change24h": 0
      },
      "narrative": "HOLD OKB (100% treasury) via okx · Price stable with balanced risk mode. Analyst recommends waiting. Confidence score is 0.8."
    }
  },
  "slowSquadLastRunAt": {
    "phantom_last_run": 1776094313252,
    "cipher_last_run": 1776094313252,
    "nexus_last_run": 1776094313253
  },
  "uniswapQueriesSuccessful": 0,
  "agentLog": [
    {
      "agent": "system",
      "status": "started",
      "completedAt": 1776094283797,
      "summary": "Cycle 192 started. Oracle snapshot in progress."
    },
    {
      "agent": "oracle",
      "status": "complete",
      "completedAt": 1776094308045,
      "summary": "ETH $0.00 (0.00%) | Uniswap spread 0.00bps"
    },
    {
      "agent": "analyst",
      "status": "complete",
      "completedAt": 1776094308965,
      "summary": "wait on ETH | confidence 0"
    },
    {
      "agent": "strategist",
      "status": "complete",
      "completedAt": 1776094309797,
      "summary": "HOLD ETH (0% treasury)"
    },
    {
      "agent": "router",
      "status": "complete",
      "completedAt": 1776094310600,
      "summary": "okx selected | spread 0.00bps"
    },
    {
      "agent": "executor",
      "status": "complete",
      "completedAt": 1776094311391,
      "summary": "HOLD executed | tx 0x4c96fdf2bf4a3c46df49e0b60d73083d2785eda4894b642067dd6fd3abe332bb"
    },
    {
      "agent": "narrator",
      "status": "complete",
      "completedAt": 1776094312427,
      "summary": "Xyndicate Alpha deployed ETH (100% treasury) via okx. Positive 24h price change and potential arbitrage opportunity through Uniswap with high confidence level. | Squad Nova held OKB (100% treasury) via okx. Price stable with balanced risk mode. Analyst recommends waiting. Confidence score is 0.8."
    },
    {
      "agent": "slow-phantom",
      "status": "complete",
      "completedAt": 1776094313252,
      "summary": "Phantom Protocol decision logged"
    },
    {
      "agent": "slow-cipher",
      "status": "complete",
      "completedAt": 1776094313252,
      "summary": "Cipher Strategy decision logged"
    },
    {
      "agent": "slow-nexus",
      "status": "complete",
      "completedAt": 1776094313253,
      "summary": "Nexus Quant decision logged"
    },
    {
      "agent": "system",
      "status": "complete",
      "completedAt": 1776094325536,
      "summary": "Cycle 192 complete. Awaiting next scheduled run."
    }
  ]
}
