{
  "currentAgent": "oracle",
  "cycleNumber": 394,
  "cycleStartTime": 1776813630059,
  "nextCycleTime": 1776815430059,
  "lastCycleComplete": 1776811810014,
  "activeSquads": [
    "Xyndicate Alpha",
    "Squad Nova"
  ],
  "squadResults": {},
  "slowSquadLastRunAt": {},
  "uniswapQueriesSuccessful": 0,
  "uniswapQueriesTotal": 2,
  "agentLog": [
    {
      "agent": "system",
      "status": "started",
      "completedAt": 1776813630059,
      "summary": "Cycle 394 started. Oracle snapshot in progress."
    }
  ]
}
