{
  "lastUpdated": 1776709416945,
  "initialized": true,
  "squads": {
    "XYNDICATE_ALPHA": {
      "startingUsdc": 1000,
      "currentTreasury": 1000.463,
      "realizedPnl": 0,
      "unrealizedPnl": 0.463,
      "roi": 0.0463,
      "openPositions": [
        {
          "asset": "ETH",
          "entryPrice": 2321.6,
          "markPrice": 2332.35,
          "sizeUsdc": 50,
          "openedAt": 1776707481733,
          "cycleNumber": 25
        },
        {
          "asset": "ETH",
          "entryPrice": 2321.6,
          "markPrice": 2332.35,
          "sizeUsdc": 50,
          "openedAt": 1776707536206,
          "cycleNumber": 26
        }
      ],
      "tradeHistory": [
        {
          "action": "BUY",
          "asset": "ETH",
          "entryPrice": 2321.6,
          "exitPrice": null,
          "sizeUsdc": 50,
          "pnl": null,
          "timestamp": 1776707481733
        },
        {
          "action": "BUY",
          "asset": "ETH",
          "entryPrice": 2321.6,
          "exitPrice": null,
          "sizeUsdc": 50,
          "pnl": null,
          "timestamp": 1776707536206
        }
      ],
      "treasuryHistory": [
        1000,
        1000,
        1000,
        1000,
        1000,
        1000,
        1000,
        1000,
        1000,
        1000,
        1000,
        1000,
        1000,
        1000,
        1000,
        1000,
        1000,
        1000,
        1000,
        1000,
        1000,
        1000,
        1000,
        1000,
        1000,
        1000,
        1000,
        1000.463,
        1000.463
      ],
      "refillCount": 0,
      "lastRefillAt": null,
      "wipedAt": null,
      "resetAt": 1776464798059,
      "resetReason": "treasury-mechanics-rewrite-v2",
      "cycleCount": 28
    },
    "SQUAD_NOVA": {
      "startingUsdc": 1000,
      "currentTreasury": 1000.2512,
      "realizedPnl": 0,
      "unrealizedPnl": 0.2512,
      "roi": 0.0251,
      "openPositions": [
        {
          "asset": "OKB",
          "entryPrice": 83.61,
          "markPrice": 83.82,
          "sizeUsdc": 50,
          "openedAt": 1776707493386,
          "cycleNumber": 25
        },
        {
          "asset": "OKB",
          "entryPrice": 83.61,
          "markPrice": 83.82,
          "sizeUsdc": 50,
          "openedAt": 1776707537088,
          "cycleNumber": 26
        }
      ],
      "tradeHistory": [
        {
          "action": "BUY",
          "asset": "OKB",
          "entryPrice": 83.61,
          "exitPrice": null,
          "sizeUsdc": 50,
          "pnl": null,
          "timestamp": 1776707493386
        },
        {
          "action": "BUY",
          "asset": "OKB",
          "entryPrice": 83.61,
          "exitPrice": null,
          "sizeUsdc": 50,
          "pnl": null,
          "timestamp": 1776707537088
        }
      ],
      "treasuryHistory": [
        1000,
        1000,
        1000,
        1000,
        1000,
        1000,
        1000,
        1000,
        1000,
        1000,
        1000,
        1000,
        1000,
        1000,
        1000,
        1000,
        1000,
        1000,
        1000,
        1000,
        1000,
        1000,
        1000,
        1000,
        1000,
        1000,
        1000,
        1000.2512
      ],
      "refillCount": 0,
      "lastRefillAt": null,
      "wipedAt": null,
      "resetAt": 1776464798059,
      "resetReason": "treasury-mechanics-rewrite-v2",
      "cycleCount": 27
    },
    "VIVAX": {
      "startingUsdc": 1000,
      "currentTreasury": 1000,
      "realizedPnl": 0,
      "unrealizedPnl": 0,
      "roi": 0,
      "openPositions": [],
      "tradeHistory": [],
      "treasuryHistory": [
        1000
      ],
      "cycleCount": 0,
      "wipedAt": null,
      "resetAt": 1776464798059,
      "resetReason": "treasury-mechanics-rewrite-v2"
    },
    "FRANCC_ALPHA": {
      "startingUsdc": 1000,
      "currentTreasury": 1000,
      "realizedPnl": 0,
      "unrealizedPnl": 0,
      "roi": 0,
      "openPositions": [],
      "tradeHistory": [],
      "treasuryHistory": [
        1000
      ],
      "cycleCount": 13,
      "wipedAt": null,
      "resetAt": 1776464798059,
      "resetReason": "treasury-mechanics-rewrite-v2",
      "refillCount": 0
    },
    "SPARTAN_ONE": {
      "startingUsdc": 1000,
      "currentTreasury": 1000,
      "realizedPnl": 0,
      "unrealizedPnl": 0,
      "roi": 0,
      "openPositions": [],
      "tradeHistory": [],
      "treasuryHistory": [
        1000
      ],
      "cycleCount": 13,
      "wipedAt": null,
      "resetAt": 1776464798059,
      "resetReason": "treasury-mechanics-rewrite-v2",
      "refillCount": 0
    }
  }
}
