{
  "lastUpdated": 1776443941066,
  "initialized": true,
  "squads": {
    "XYNDICATE_ALPHA": {
      "startingUsdc": 1000,
      "currentTreasury": 0,
      "realizedPnl": 0,
      "unrealizedPnl": -1000,
      "roi": -100,
      "openPositions": [
        {
          "asset": "ETH",
          "entryPrice": 2442,
          "allocationUsdc": 1000,
          "openedAt": 1776434514945
        }
      ],
      "tradeHistory": [
        {
          "action": "BUY",
          "asset": "ETH",
          "price": 2442,
          "allocationUsdc": 1000,
          "pnl": null,
          "timestamp": 1776434514945
        }
      ],
      "treasuryHistory": [
        1000,
        1000,
        1000,
        1000,
        1000,
        1000,
        1000,
        1000,
        1000,
        1000,
        1000,
        1000,
        1000,
        1000,
        1000,
        1000,
        1000,
        1000,
        1000,
        1000,
        1000,
        1000,
        1000,
        1000,
        1000,
        1000,
        1000,
        1000,
        1000,
        1000,
        1000,
        1000,
        1000,
        1000,
        1000,
        1000,
        1000,
        1000,
        0,
        999.0008,
        0,
        996.4906,
        0,
        1002.2031,
        0,
        1002.4079,
        0,
        1008.2719,
        0
      ],
      "refillCount": 0,
      "lastRefillAt": null,
      "wipedAt": 1776443935862,
      "resetAt": 1776364853141,
      "resetReason": "treasury-reset-v1"
    },
    "SQUAD_NOVA": {
      "startingUsdc": 1000,
      "currentTreasury": 0,
      "realizedPnl": 0,
      "unrealizedPnl": -1000,
      "roi": -100,
      "openPositions": [
        {
          "asset": "OKB",
          "entryPrice": 87.42,
          "allocationUsdc": 1000,
          "openedAt": 1776434530134
        }
      ],
      "tradeHistory": [
        {
          "action": "BUY",
          "asset": "OKB",
          "price": 87.42,
          "allocationUsdc": 1000,
          "pnl": null,
          "timestamp": 1776434530134
        }
      ],
      "treasuryHistory": [
        1000,
        1000,
        1000,
        1000,
        1000,
        1000,
        1000,
        1000,
        1000,
        1000,
        1000,
        1000,
        1000,
        1000,
        1000,
        1000,
        1000,
        1000,
        1000,
        1000,
        1000,
        1000,
        1000,
        1000,
        1000,
        1000,
        1000,
        1000,
        1000,
        1000,
        1000,
        1000,
        1000,
        1000,
        1000,
        1000,
        1000,
        1000,
        0,
        998.6273,
        0,
        997.0259,
        0,
        994.1661,
        0,
        995.0812,
        0,
        998.0554,
        0
      ],
      "refillCount": 0,
      "lastRefillAt": null,
      "wipedAt": 1776443936462,
      "resetAt": 1776364853141,
      "resetReason": "treasury-reset-v1"
    },
    "VIVAX": {
      "startingUsdc": 1000,
      "currentTreasury": 1000,
      "realizedPnl": 0,
      "unrealizedPnl": 0,
      "roi": 0,
      "openPositions": [],
      "tradeHistory": [],
      "treasuryHistory": [
        1000,
        1000
      ]
    },
    "FRANCC_ALPHA": {
      "startingUsdc": 1000,
      "currentTreasury": 1000,
      "realizedPnl": 0,
      "unrealizedPnl": 0,
      "roi": 0,
      "openPositions": [],
      "tradeHistory": [],
      "treasuryHistory": [
        1000,
        1000,
        1000,
        1000,
        1000,
        1000,
        1000,
        1000,
        1000,
        1000,
        1000,
        1000
      ]
    },
    "SPARTAN_ONE": {
      "startingUsdc": 1000,
      "currentTreasury": 1000,
      "realizedPnl": 0,
      "unrealizedPnl": 0,
      "roi": 0,
      "openPositions": [],
      "tradeHistory": [],
      "treasuryHistory": [
        1000,
        1000,
        1000,
        1000,
        1000,
        1000,
        1000,
        1000,
        1000,
        1000,
        1000
      ]
    }
  }
}
