{
  "lastUpdated": 1776724555396,
  "initialized": true,
  "squads": {
    "XYNDICATE_ALPHA": {
      "startingUsdc": 1000,
      "currentTreasury": 999.8031,
      "realizedPnl": -0.2081,
      "unrealizedPnl": 0.0112,
      "roi": -0.0197,
      "openPositions": [
        {
          "asset": "ETH",
          "entryPrice": 2323.15,
          "markPrice": 2323.41,
          "sizeUsdc": 50,
          "openedAt": 1776722607586,
          "cycleNumber": 41
        },
        {
          "asset": "ETH",
          "entryPrice": 2323.15,
          "markPrice": 2323.41,
          "sizeUsdc": 50,
          "openedAt": 1776722663179,
          "cycleNumber": 42
        }
      ],
      "tradeHistory": [
        {
          "action": "BUY",
          "asset": "ETH",
          "entryPrice": 2321.6,
          "exitPrice": null,
          "sizeUsdc": 50,
          "pnl": null,
          "timestamp": 1776707481733
        },
        {
          "action": "BUY",
          "asset": "ETH",
          "entryPrice": 2321.6,
          "exitPrice": null,
          "sizeUsdc": 50,
          "pnl": null,
          "timestamp": 1776707536206
        },
        {
          "action": "SELL",
          "asset": "ETH",
          "entryPrice": 2321.6,
          "exitPrice": 2327.65,
          "sizeUsdc": 50,
          "pnl": 0.1303,
          "timestamp": 1776715033149,
          "reason": "force-close-stale"
        },
        {
          "action": "BUY",
          "asset": "ETH",
          "entryPrice": 2333.74,
          "exitPrice": null,
          "sizeUsdc": 50,
          "pnl": null,
          "timestamp": 1776715033149
        },
        {
          "action": "SELL",
          "asset": "ETH",
          "entryPrice": 2321.6,
          "exitPrice": 2333.74,
          "sizeUsdc": 50,
          "pnl": 0.2615,
          "timestamp": 1776715091985,
          "reason": "force-close-stale"
        },
        {
          "action": "BUY",
          "asset": "ETH",
          "entryPrice": 2333.74,
          "exitPrice": null,
          "sizeUsdc": 50,
          "pnl": null,
          "timestamp": 1776715091985
        },
        {
          "action": "SELL",
          "asset": "ETH",
          "entryPrice": 2333.74,
          "exitPrice": 2316.33,
          "sizeUsdc": 50,
          "pnl": -0.373,
          "timestamp": 1776722607586,
          "reason": "force-close-stale"
        },
        {
          "action": "BUY",
          "asset": "ETH",
          "entryPrice": 2323.15,
          "exitPrice": null,
          "sizeUsdc": 50,
          "pnl": null,
          "timestamp": 1776722607586
        },
        {
          "action": "SELL",
          "asset": "ETH",
          "entryPrice": 2333.74,
          "exitPrice": 2323.15,
          "sizeUsdc": 50,
          "pnl": -0.2269,
          "timestamp": 1776722663179,
          "reason": "force-close-stale"
        },
        {
          "action": "BUY",
          "asset": "ETH",
          "entryPrice": 2323.15,
          "exitPrice": null,
          "sizeUsdc": 50,
          "pnl": null,
          "timestamp": 1776722663179
        }
      ],
      "treasuryHistory": [
        1000,
        1000,
        1000,
        1000,
        1000,
        1000,
        1000,
        1000,
        1000,
        1000,
        1000,
        1000,
        1000,
        1000,
        1000,
        1000,
        1000,
        1000,
        1000,
        1000,
        1000,
        1000,
        1000,
        1000,
        1000,
        1000,
        1000,
        1000.463,
        1000.463,
        1000.6728,
        1000.6728,
        1000.2606,
        1000.2606,
        1000.3918,
        1000.3918,
        1000.2718,
        1000.2718,
        1000.5889,
        1000.5889,
        999.6458,
        999.6458,
        999.7919,
        999.7919,
        999.8031,
        999.8031
      ],
      "refillCount": 0,
      "lastRefillAt": null,
      "wipedAt": null,
      "resetAt": 1776464798059,
      "resetReason": "treasury-mechanics-rewrite-v2",
      "cycleCount": 44
    },
    "SQUAD_NOVA": {
      "startingUsdc": 1000,
      "currentTreasury": 1000.03,
      "realizedPnl": 0.1375,
      "unrealizedPnl": -0.1075,
      "roi": 0.003,
      "openPositions": [
        {
          "asset": "OKB",
          "entryPrice": 83.75,
          "markPrice": 83.66,
          "sizeUsdc": 50,
          "openedAt": 1776722621863,
          "cycleNumber": 41
        },
        {
          "asset": "OKB",
          "entryPrice": 83.75,
          "markPrice": 83.66,
          "sizeUsdc": 50,
          "openedAt": 1776722664091,
          "cycleNumber": 42
        }
      ],
      "tradeHistory": [
        {
          "action": "BUY",
          "asset": "OKB",
          "entryPrice": 83.61,
          "exitPrice": null,
          "sizeUsdc": 50,
          "pnl": null,
          "timestamp": 1776707493386
        },
        {
          "action": "BUY",
          "asset": "OKB",
          "entryPrice": 83.61,
          "exitPrice": null,
          "sizeUsdc": 50,
          "pnl": null,
          "timestamp": 1776707537088
        },
        {
          "action": "SELL",
          "asset": "OKB",
          "entryPrice": 83.61,
          "exitPrice": 83.75,
          "sizeUsdc": 50,
          "pnl": 0.0837,
          "timestamp": 1776715049726,
          "reason": "force-close-stale"
        },
        {
          "action": "SELL",
          "asset": "OKB",
          "entryPrice": 83.61,
          "exitPrice": 83.7,
          "sizeUsdc": 50,
          "pnl": 0.0538,
          "timestamp": 1776715092873,
          "reason": "force-close-stale"
        },
        {
          "action": "BUY",
          "asset": "OKB",
          "entryPrice": 83.75,
          "exitPrice": null,
          "sizeUsdc": 50,
          "pnl": null,
          "timestamp": 1776722621863
        },
        {
          "action": "BUY",
          "asset": "OKB",
          "entryPrice": 83.75,
          "exitPrice": null,
          "sizeUsdc": 50,
          "pnl": null,
          "timestamp": 1776722664091
        }
      ],
      "treasuryHistory": [
        1000,
        1000,
        1000,
        1000,
        1000,
        1000,
        1000,
        1000,
        1000,
        1000,
        1000,
        1000,
        1000,
        1000,
        1000,
        1000,
        1000,
        1000,
        1000,
        1000,
        1000,
        1000,
        1000,
        1000,
        1000,
        1000,
        1000,
        1000.2512,
        1000.2512,
        1000.2033,
        1000.2033,
        1000.1674,
        1000.1674,
        1000.1375,
        1000.1375,
        1000.1375,
        1000.1375,
        1000.1375,
        1000.1375,
        1000.1375,
        1000.1375,
        1000.1375,
        1000.1375,
        1000.03
      ],
      "refillCount": 0,
      "lastRefillAt": null,
      "wipedAt": null,
      "resetAt": 1776464798059,
      "resetReason": "treasury-mechanics-rewrite-v2",
      "cycleCount": 43
    },
    "VIVAX": {
      "startingUsdc": 1000,
      "currentTreasury": 1000,
      "realizedPnl": 0,
      "unrealizedPnl": 0,
      "roi": 0,
      "openPositions": [],
      "tradeHistory": [],
      "treasuryHistory": [
        1000
      ],
      "cycleCount": 0,
      "wipedAt": null,
      "resetAt": 1776464798059,
      "resetReason": "treasury-mechanics-rewrite-v2"
    },
    "FRANCC_ALPHA": {
      "startingUsdc": 1000,
      "currentTreasury": 1000,
      "realizedPnl": 0,
      "unrealizedPnl": 0,
      "roi": 0,
      "openPositions": [],
      "tradeHistory": [],
      "treasuryHistory": [
        1000
      ],
      "cycleCount": 21,
      "wipedAt": null,
      "resetAt": 1776464798059,
      "resetReason": "treasury-mechanics-rewrite-v2",
      "refillCount": 0
    },
    "SPARTAN_ONE": {
      "startingUsdc": 1000,
      "currentTreasury": 1000,
      "realizedPnl": 0,
      "unrealizedPnl": 0,
      "roi": 0,
      "openPositions": [],
      "tradeHistory": [],
      "treasuryHistory": [
        1000
      ],
      "cycleCount": 21,
      "wipedAt": null,
      "resetAt": 1776464798059,
      "resetReason": "treasury-mechanics-rewrite-v2",
      "refillCount": 0
    }
  }
}
